Workbook

Sheet One Piece
A1: KEN JP ANIME FIGURES SHOP
A4: 📦 ONE PIECE INVENTORY LOG | J4: Live JPY/PHP Rate: | K4: 0.37 | L4: ← Edit here
A5: 🔍 QUICK-VIEW LOOKUP: | C5: ← Select Product ID | E5: =IFERROR(VLOOKUP(C5,A8:L57,4,0),"") | F5: =IFERROR(VLOOKUP(C5,A8:L57,5,0),"") | G5: =IFERROR(VLOOKUP(C5,A8:L57,6,0),"") | H5: =IFERROR(VLOOKUP(C5,A8:L57,7,0),"") | I5: =IFERROR(VLOOKUP(C5,A8:L57,8,0),"") | J5: =IFERROR(VLOOKUP(C5,A8:L57,9,0),"") | K5: =IFERROR(VLOOKUP(C5,A8:L57,10,0),"") | L5: =IFERROR(VLOOKUP(C5,A8:L57,11,0),"")
A7: Product ID | B7: Date of Entry | C7: Transaction Month | D7: Purchase Price (JPY) | E7: Purchase Price (PHP) | F7: Selling Price (JPY) | G7: Selling Price (PHP) | H7: Net Profit (JPY) | I7: Net Profit (PHP) | J7: Net Loss (JPY) | K7: Net Loss (PHP) | L7: Stock Status
A8: OP1 | C8: =IF(B8="","",TEXT(B8,"mmmm")) | E8: =IF(D8="","",D8*$K$4) | G8: =IF(F8="","",F8*$K$4) | H8: =IF(L8="Inactive",0,IF(F8>D8,F8-D8,0)) -> 0 | I8: =IF(L8="Inactive",0,IF(G8>E8,G8-E8,0)) -> 0 | J8: =IF(L8="Inactive",0,IF(D8>F8,D8-F8,0)) -> 0 | K8: =IF(L8="Inactive",0,IF(E8>G8,E8-G8,0)) -> 0 | L8: Active
A9: OP2 | C9: =IF(B9="","",TEXT(B9,"mmmm")) | E9: =IF(D9="","",D9*$K$4) | G9: =IF(F9="","",F9*$K$4) | H9: =IF(L9="Inactive",0,IF(F9>D9,F9-D9,0)) -> 0 | I9: =IF(L9="Inactive",0,IF(G9>E9,G9-E9,0)) -> 0 | J9: =IF(L9="Inactive",0,IF(D9>F9,D9-F9,0)) -> 0 | K9: =IF(L9="Inactive",0,IF(E9>G9,E9-G9,0)) -> 0 | L9: Active
A10: OP3 | C10: =IF(B10="","",TEXT(B10,"mmmm")) | E10: =IF(D10="","",D10*$K$4) | G10: =IF(F10="","",F10*$K$4) | H10: =IF(L10="Inactive",0,IF(F10>D10,F10-D10,0)) -> 0 | I10: =IF(L10="Inactive",0,IF(G10>E10,G10-E10,0)) -> 0 | J10: =IF(L10="Inactive",0,IF(D10>F10,D10-F10,0)) -> 0 | K10: =IF(L10="Inactive",0,IF(E10>G10,E10-G10,0)) -> 0 | L10: Active
A11: OP4 | C11: =IF(B11="","",TEXT(B11,"mmmm")) | E11: =IF(D11="","",D11*$K$4) | G11: =IF(F11="","",F11*$K$4) | H11: =IF(L11="Inactive",0,IF(F11>D11,F11-D11,0)) -> 0 | I11: =IF(L11="Inactive",0,IF(G11>E11,G11-E11,0)) -> 0 | J11: =IF(L11="Inactive",0,IF(D11>F11,D11-F11,0)) -> 0 | K11: =IF(L11="Inactive",0,IF(E11>G11,E11-G11,0)) -> 0 | L11: Active
A12: OP5 | C12: =IF(B12="","",TEXT(B12,"mmmm")) | E12: =IF(D12="","",D12*$K$4) | G12: =IF(F12="","",F12*$K$4) | H12: =IF(L12="Inactive",0,IF(F12>D12,F12-D12,0)) -> 0 | I12: =IF(L12="Inactive",0,IF(G12>E12,G12-E12,0)) -> 0 | J12: =IF(L12="Inactive",0,IF(D12>F12,D12-F12,0)) -> 0 | K12: =IF(L12="Inactive",0,IF(E12>G12,E12-G12,0)) -> 0 | L12: Active
A13: OP6 | C13: =IF(B13="","",TEXT(B13,"mmmm")) | E13: =IF(D13="","",D13*$K$4) | G13: =IF(F13="","",F13*$K$4) | H13: =IF(L13="Inactive",0,IF(F13>D13,F13-D13,0)) -> 0 | I13: =IF(L13="Inactive",0,IF(G13>E13,G13-E13,0)) -> 0 | J13: =IF(L13="Inactive",0,IF(D13>F13,D13-F13,0)) -> 0 | K13: =IF(L13="Inactive",0,IF(E13>G13,E13-G13,0)) -> 0 | L13: Active
A14: OP7 | C14: =IF(B14="","",TEXT(B14,"mmmm")) | E14: =IF(D14="","",D14*$K$4) | G14: =IF(F14="","",F14*$K$4) | H14: =IF(L14="Inactive",0,IF(F14>D14,F14-D14,0)) -> 0 | I14: =IF(L14="Inactive",0,IF(G14>E14,G14-E14,0)) -> 0 | J14: =IF(L14="Inactive",0,IF(D14>F14,D14-F14,0)) -> 0 | K14: =IF(L14="Inactive",0,IF(E14>G14,E14-G14,0)) -> 0 | L14: Active
A15: OP8 | C15: =IF(B15="","",TEXT(B15,"mmmm")) | E15: =IF(D15="","",D15*$K$4) | G15: =IF(F15="","",F15*$K$4) | H15: =IF(L15="Inactive",0,IF(F15>D15,F15-D15,0)) -> 0 | I15: =IF(L15="Inactive",0,IF(G15>E15,G15-E15,0)) -> 0 | J15: =IF(L15="Inactive",0,IF(D15>F15,D15-F15,0)) -> 0 | K15: =IF(L15="Inactive",0,IF(E15>G15,E15-G15,0)) -> 0 | L15: Active
A16: OP9 | C16: =IF(B16="","",TEXT(B16,"mmmm")) | E16: =IF(D16="","",D16*$K$4) | G16: =IF(F16="","",F16*$K$4) | H16: =IF(L16="Inactive",0,IF(F16>D16,F16-D16,0)) -> 0 | I16: =IF(L16="Inactive",0,IF(G16>E16,G16-E16,0)) -> 0 | J16: =IF(L16="Inactive",0,IF(D16>F16,D16-F16,0)) -> 0 | K16: =IF(L16="Inactive",0,IF(E16>G16,E16-G16,0)) -> 0 | L16: Active
A17: OP10 | C17: =IF(B17="","",TEXT(B17,"mmmm")) | E17: =IF(D17="","",D17*$K$4) | G17: =IF(F17="","",F17*$K$4) | H17: =IF(L17="Inactive",0,IF(F17>D17,F17-D17,0)) -> 0 | I17: =IF(L17="Inactive",0,IF(G17>E17,G17-E17,0)) -> 0 | J17: =IF(L17="Inactive",0,IF(D17>F17,D17-F17,0)) -> 0 | K17: =IF(L17="Inactive",0,IF(E17>G17,E17-G17,0)) -> 0 | L17: Active
A18: OP11 | C18: =IF(B18="","",TEXT(B18,"mmmm")) | E18: =IF(D18="","",D18*$K$4) | G18: =IF(F18="","",F18*$K$4) | H18: =IF(L18="Inactive",0,IF(F18>D18,F18-D18,0)) -> 0 | I18: =IF(L18="Inactive",0,IF(G18>E18,G18-E18,0)) -> 0 | J18: =IF(L18="Inactive",0,IF(D18>F18,D18-F18,0)) -> 0 | K18: =IF(L18="Inactive",0,IF(E18>G18,E18-G18,0)) -> 0 | L18: Active
A19: OP12 | C19: =IF(B19="","",TEXT(B19,"mmmm")) | E19: =IF(D19="","",D19*$K$4) | G19: =IF(F19="","",F19*$K$4) | H19: =IF(L19="Inactive",0,IF(F19>D19,F19-D19,0)) -> 0 | I19: =IF(L19="Inactive",0,IF(G19>E19,G19-E19,0)) -> 0 | J19: =IF(L19="Inactive",0,IF(D19>F19,D19-F19,0)) -> 0 | K19: =IF(L19="Inactive",0,IF(E19>G19,E19-G19,0)) -> 0 | L19: Active
... A57: OP50 | C57: =IF(B57="","",TEXT(B57,"mmmm")) | E57: =IF(D57="","",D57*$K$4) | G57: =IF(F57="","",F57*$K$4) | H57: =IF(L57="Inactive",0,IF(F57>D57,F57-D57,0)) -> 0 | I57: =IF(L57="Inactive",0,IF(G57>E57,G57-E57,0)) -> 0 | J57: =IF(L57="Inactive",0,IF(D57>F57,D57-F57,0)) -> 0 | K57: =IF(L57="Inactive",0,IF(E57>G57,E57-G57,0)) -> 0 | L57: Active
A58: TOTAL CATEGORY VALUE | D58: =SUM(D8:D57) -> 0 | E58: =SUM(E8:E57) -> 0 | F58: =SUM(F8:F57) -> 0 | G58: =SUM(G8:G57) -> 0 | H58: =SUM(H8:H57) -> 0 | I58: =SUM(I8:I57) -> 0 | J58: =SUM(J8:J57) -> 0 | K58: =SUM(K8:K57) -> 0
A60: 📋 USER GUIDE & OPERATIONAL INSTRUCTIONS
A61: Step 1 — DATA ENTRY
A62: ONLY fill data into columns: 'Product ID' (pre-filled), 'Date of Entry' (Col B), 'Purchase Price JPY' (Col D), and 'Selling Price JPY' (Col F). Do NOT overwrite any other cells — they contain automated formulas!
A63: Step 2 — AUTO DATE TRACKING
A64: The system automatically reads your Date of Entry and extracts the full calendar month name in Column C behind the scenes. No manual entry needed.
A65: Step 3 — AUTO CALCULATIONS
A66: All PHP conversions (Cols E & G), dynamic profit calculations (Cols H & I), and loss flags (Cols J & K) recalculate INSTANTLY whenever you enter or update data.
A67: Step 4 — STOCK STATUS CONTROL
A68: Use the interactive drop-down menu in Column L ('Stock Status') to switch rows between 'Active' and 'Inactive'. Setting a row to 'Inactive' instantly zeroes out its profit and loss contributions from all totals.
A69: Step 5 — QUICK-VIEW LOOKUP
A70: Use the 🔍 dropdown in Cell C5 to instantly surface real-time financial data for any product without scrolling. Results appear in Row 5 immediately.
A71: Step 6 — EXCHANGE RATE
A72: Update Cell K4 with the current JPY/PHP exchange rate. All PHP values across the entire sheet recalculate automatically. Default is 0.37.

Sheet Dragon Ball Z
A1: KEN JP ANIME FIGURES SHOP
A4: 📦 DRAGON BALL Z INVENTORY LOG | J4: Live JPY/PHP Rate: | K4: 0.37 | L4: ← Edit here
A5: 🔍 QUICK-VIEW LOOKUP: | C5: ← Select Product ID | E5: =IFERROR(VLOOKUP(C5,A8:L57,4,0),"") | F5: =IFERROR(VLOOKUP(C5,A8:L57,5,0),"") | G5: =IFERROR(VLOOKUP(C5,A8:L57,6,0),"") | H5: =IFERROR(VLOOKUP(C5,A8:L57,7,0),"") | I5: =IFERROR(VLOOKUP(C5,A8:L57,8,0),"") | J5: =IFERROR(VLOOKUP(C5,A8:L57,9,0),"") | K5: =IFERROR(VLOOKUP(C5,A8:L57,10,0),"") | L5: =IFERROR(VLOOKUP(C5,A8:L57,11,0),"")
A7: Product ID | B7: Date of Entry | C7: Transaction Month | D7: Purchase Price (JPY) | E7: Purchase Price (PHP) | F7: Selling Price (JPY) | G7: Selling Price (PHP) | H7: Net Profit (JPY) | I7: Net Profit (PHP) | J7: Net Loss (JPY) | K7: Net Loss (PHP) | L7: Stock Status
A8: DBZ1 | C8: =IF(B8="","",TEXT(B8,"mmmm")) | E8: =IF(D8="","",D8*$K$4) | G8: =IF(F8="","",F8*$K$4) | H8: =IF(L8="Inactive",0,IF(F8>D8,F8-D8,0)) -> 0 | I8: =IF(L8="Inactive",0,IF(G8>E8,G8-E8,0)) -> 0 | J8: =IF(L8="Inactive",0,IF(D8>F8,D8-F8,0)) -> 0 | K8: =IF(L8="Inactive",0,IF(E8>G8,E8-G8,0)) -> 0 | L8: Active
A9: DBZ2 | C9: =IF(B9="","",TEXT(B9,"mmmm")) | E9: =IF(D9="","",D9*$K$4) | G9: =IF(F9="","",F9*$K$4) | H9: =IF(L9="Inactive",0,IF(F9>D9,F9-D9,0)) -> 0 | I9: =IF(L9="Inactive",0,IF(G9>E9,G9-E9,0)) -> 0 | J9: =IF(L9="Inactive",0,IF(D9>F9,D9-F9,0)) -> 0 | K9: =IF(L9="Inactive",0,IF(E9>G9,E9-G9,0)) -> 0 | L9: Active
A10: DBZ3 | C10: =IF(B10="","",TEXT(B10,"mmmm")) | E10: =IF(D10="","",D10*$K$4) | G10: =IF(F10="","",F10*$K$4) | H10: =IF(L10="Inactive",0,IF(F10>D10,F10-D10,0)) -> 0 | I10: =IF(L10="Inactive",0,IF(G10>E10,G10-E10,0)) -> 0 | J10: =IF(L10="Inactive",0,IF(D10>F10,D10-F10,0)) -> 0 | K10: =IF(L10="Inactive",0,IF(E10>G10,E10-G10,0)) -> 0 | L10: Active
A11: DBZ4 | C11: =IF(B11="","",TEXT(B11,"mmmm")) | E11: =IF(D11="","",D11*$K$4) | G11: =IF(F11="","",F11*$K$4) | H11: =IF(L11="Inactive",0,IF(F11>D11,F11-D11,0)) -> 0 | I11: =IF(L11="Inactive",0,IF(G11>E11,G11-E11,0)) -> 0 | J11: =IF(L11="Inactive",0,IF(D11>F11,D11-F11,0)) -> 0 | K11: =IF(L11="Inactive",0,IF(E11>G11,E11-G11,0)) -> 0 | L11: Active
A12: DBZ5 | C12: =IF(B12="","",TEXT(B12,"mmmm")) | E12: =IF(D12="","",D12*$K$4) | G12: =IF(F12="","",F12*$K$4) | H12: =IF(L12="Inactive",0,IF(F12>D12,F12-D12,0)) -> 0 | I12: =IF(L12="Inactive",0,IF(G12>E12,G12-E12,0)) -> 0 | J12: =IF(L12="Inactive",0,IF(D12>F12,D12-F12,0)) -> 0 | K12: =IF(L12="Inactive",0,IF(E12>G12,E12-G12,0)) -> 0 | L12: Active
A13: DBZ6 | C13: =IF(B13="","",TEXT(B13,"mmmm")) | E13: =IF(D13="","",D13*$K$4) | G13: =IF(F13="","",F13*$K$4) | H13: =IF(L13="Inactive",0,IF(F13>D13,F13-D13,0)) -> 0 | I13: =IF(L13="Inactive",0,IF(G13>E13,G13-E13,0)) -> 0 | J13: =IF(L13="Inactive",0,IF(D13>F13,D13-F13,0)) -> 0 | K13: =IF(L13="Inactive",0,IF(E13>G13,E13-G13,0)) -> 0 | L13: Active
A14: DBZ7 | C14: =IF(B14="","",TEXT(B14,"mmmm")) | E14: =IF(D14="","",D14*$K$4) | G14: =IF(F14="","",F14*$K$4) | H14: =IF(L14="Inactive",0,IF(F14>D14,F14-D14,0)) -> 0 | I14: =IF(L14="Inactive",0,IF(G14>E14,G14-E14,0)) -> 0 | J14: =IF(L14="Inactive",0,IF(D14>F14,D14-F14,0)) -> 0 | K14: =IF(L14="Inactive",0,IF(E14>G14,E14-G14,0)) -> 0 | L14: Active
A15: DBZ8 | C15: =IF(B15="","",TEXT(B15,"mmmm")) | E15: =IF(D15="","",D15*$K$4) | G15: =IF(F15="","",F15*$K$4) | H15: =IF(L15="Inactive",0,IF(F15>D15,F15-D15,0)) -> 0 | I15: =IF(L15="Inactive",0,IF(G15>E15,G15-E15,0)) -> 0 | J15: =IF(L15="Inactive",0,IF(D15>F15,D15-F15,0)) -> 0 | K15: =IF(L15="Inactive",0,IF(E15>G15,E15-G15,0)) -> 0 | L15: Active
A16: DBZ9 | C16: =IF(B16="","",TEXT(B16,"mmmm")) | E16: =IF(D16="","",D16*$K$4) | G16: =IF(F16="","",F16*$K$4) | H16: =IF(L16="Inactive",0,IF(F16>D16,F16-D16,0)) -> 0 | I16: =IF(L16="Inactive",0,IF(G16>E16,G16-E16,0)) -> 0 | J16: =IF(L16="Inactive",0,IF(D16>F16,D16-F16,0)) -> 0 | K16: =IF(L16="Inactive",0,IF(E16>G16,E16-G16,0)) -> 0 | L16: Active
A17: DBZ10 | C17: =IF(B17="","",TEXT(B17,"mmmm")) | E17: =IF(D17="","",D17*$K$4) | G17: =IF(F17="","",F17*$K$4) | H17: =IF(L17="Inactive",0,IF(F17>D17,F17-D17,0)) -> 0 | I17: =IF(L17="Inactive",0,IF(G17>E17,G17-E17,0)) -> 0 | J17: =IF(L17="Inactive",0,IF(D17>F17,D17-F17,0)) -> 0 | K17: =IF(L17="Inactive",0,IF(E17>G17,E17-G17,0)) -> 0 | L17: Active
A18: DBZ11 | C18: =IF(B18="","",TEXT(B18,"mmmm")) | E18: =IF(D18="","",D18*$K$4) | G18: =IF(F18="","",F18*$K$4) | H18: =IF(L18="Inactive",0,IF(F18>D18,F18-D18,0)) -> 0 | I18: =IF(L18="Inactive",0,IF(G18>E18,G18-E18,0)) -> 0 | J18: =IF(L18="Inactive",0,IF(D18>F18,D18-F18,0)) -> 0 | K18: =IF(L18="Inactive",0,IF(E18>G18,E18-G18,0)) -> 0 | L18: Active
A19: DBZ12 | C19: =IF(B19="","",TEXT(B19,"mmmm")) | E19: =IF(D19="","",D19*$K$4) | G19: =IF(F19="","",F19*$K$4) | H19: =IF(L19="Inactive",0,IF(F19>D19,F19-D19,0)) -> 0 | I19: =IF(L19="Inactive",0,IF(G19>E19,G19-E19,0)) -> 0 | J19: =IF(L19="Inactive",0,IF(D19>F19,D19-F19,0)) -> 0 | K19: =IF(L19="Inactive",0,IF(E19>G19,E19-G19,0)) -> 0 | L19: Active
... A57: DBZ50 | C57: =IF(B57="","",TEXT(B57,"mmmm")) | E57: =IF(D57="","",D57*$K$4) | G57: =IF(F57="","",F57*$K$4) | H57: =IF(L57="Inactive",0,IF(F57>D57,F57-D57,0)) -> 0 | I57: =IF(L57="Inactive",0,IF(G57>E57,G57-E57,0)) -> 0 | J57: =IF(L57="Inactive",0,IF(D57>F57,D57-F57,0)) -> 0 | K57: =IF(L57="Inactive",0,IF(E57>G57,E57-G57,0)) -> 0 | L57: Active
A58: TOTAL CATEGORY VALUE | D58: =SUM(D8:D57) -> 0 | E58: =SUM(E8:E57) -> 0 | F58: =SUM(F8:F57) -> 0 | G58: =SUM(G8:G57) -> 0 | H58: =SUM(H8:H57) -> 0 | I58: =SUM(I8:I57) -> 0 | J58: =SUM(J8:J57) -> 0 | K58: =SUM(K8:K57) -> 0
A60: 📋 USER GUIDE & OPERATIONAL INSTRUCTIONS
A61: Step 1 — DATA ENTRY
A62: ONLY fill data into columns: 'Product ID' (pre-filled), 'Date of Entry' (Col B), 'Purchase Price JPY' (Col D), and 'Selling Price JPY' (Col F). Do NOT overwrite any other cells — they contain automated formulas!
A63: Step 2 — AUTO DATE TRACKING
A64: The system automatically reads your Date of Entry and extracts the full calendar month name in Column C behind the scenes. No manual entry needed.
A65: Step 3 — AUTO CALCULATIONS
A66: All PHP conversions (Cols E & G), dynamic profit calculations (Cols H & I), and loss flags (Cols J & K) recalculate INSTANTLY whenever you enter or update data.
A67: Step 4 — STOCK STATUS CONTROL
A68: Use the interactive drop-down menu in Column L ('Stock Status') to switch rows between 'Active' and 'Inactive'. Setting a row to 'Inactive' instantly zeroes out its profit and loss contributions from all totals.
A69: Step 5 — QUICK-VIEW LOOKUP
A70: Use the 🔍 dropdown in Cell C5 to instantly surface real-time financial data for any product without scrolling. Results appear in Row 5 immediately.
A71: Step 6 — EXCHANGE RATE
A72: Update Cell K4 with the current JPY/PHP exchange rate. All PHP values across the entire sheet recalculate automatically. Default is 0.37.

Sheet Naruto
A1: KEN JP ANIME FIGURES SHOP
A4: 📦 NARUTO INVENTORY LOG | J4: Live JPY/PHP Rate: | K4: 0.37 | L4: ← Edit here
A5: 🔍 QUICK-VIEW LOOKUP: | C5: ← Select Product ID | E5: =IFERROR(VLOOKUP(C5,A8:L57,4,0),"") | F5: =IFERROR(VLOOKUP(C5,A8:L57,5,0),"") | G5: =IFERROR(VLOOKUP(C5,A8:L57,6,0),"") | H5: =IFERROR(VLOOKUP(C5,A8:L57,7,0),"") | I5: =IFERROR(VLOOKUP(C5,A8:L57,8,0),"") | J5: =IFERROR(VLOOKUP(C5,A8:L57,9,0),"") | K5: =IFERROR(VLOOKUP(C5,A8:L57,10,0),"") | L5: =IFERROR(VLOOKUP(C5,A8:L57,11,0),"")
A7: Product ID | B7: Date of Entry | C7: Transaction Month | D7: Purchase Price (JPY) | E7: Purchase Price (PHP) | F7: Selling Price (JPY) | G7: Selling Price (PHP) | H7: Net Profit (JPY) | I7: Net Profit (PHP) | J7: Net Loss (JPY) | K7: Net Loss (PHP) | L7: Stock Status
A8: NT1 | C8: =IF(B8="","",TEXT(B8,"mmmm")) | E8: =IF(D8="","",D8*$K$4) | G8: =IF(F8="","",F8*$K$4) | H8: =IF(L8="Inactive",0,IF(F8>D8,F8-D8,0)) -> 0 | I8: =IF(L8="Inactive",0,IF(G8>E8,G8-E8,0)) -> 0 | J8: =IF(L8="Inactive",0,IF(D8>F8,D8-F8,0)) -> 0 | K8: =IF(L8="Inactive",0,IF(E8>G8,E8-G8,0)) -> 0 | L8: Active
A9: NT2 | C9: =IF(B9="","",TEXT(B9,"mmmm")) | E9: =IF(D9="","",D9*$K$4) | G9: =IF(F9="","",F9*$K$4) | H9: =IF(L9="Inactive",0,IF(F9>D9,F9-D9,0)) -> 0 | I9: =IF(L9="Inactive",0,IF(G9>E9,G9-E9,0)) -> 0 | J9: =IF(L9="Inactive",0,IF(D9>F9,D9-F9,0)) -> 0 | K9: =IF(L9="Inactive",0,IF(E9>G9,E9-G9,0)) -> 0 | L9: Active
A10: NT3 | C10: =IF(B10="","",TEXT(B10,"mmmm")) | E10: =IF(D10="","",D10*$K$4) | G10: =IF(F10="","",F10*$K$4) | H10: =IF(L10="Inactive",0,IF(F10>D10,F10-D10,0)) -> 0 | I10: =IF(L10="Inactive",0,IF(G10>E10,G10-E10,0)) -> 0 | J10: =IF(L10="Inactive",0,IF(D10>F10,D10-F10,0)) -> 0 | K10: =IF(L10="Inactive",0,IF(E10>G10,E10-G10,0)) -> 0 | L10: Active
A11: NT4 | C11: =IF(B11="","",TEXT(B11,"mmmm")) | E11: =IF(D11="","",D11*$K$4) | G11: =IF(F11="","",F11*$K$4) | H11: =IF(L11="Inactive",0,IF(F11>D11,F11-D11,0)) -> 0 | I11: =IF(L11="Inactive",0,IF(G11>E11,G11-E11,0)) -> 0 | J11: =IF(L11="Inactive",0,IF(D11>F11,D11-F11,0)) -> 0 | K11: =IF(L11="Inactive",0,IF(E11>G11,E11-G11,0)) -> 0 | L11: Active
A12: NT5 | C12: =IF(B12="","",TEXT(B12,"mmmm")) | E12: =IF(D12="","",D12*$K$4) | G12: =IF(F12="","",F12*$K$4) | H12: =IF(L12="Inactive",0,IF(F12>D12,F12-D12,0)) -> 0 | I12: =IF(L12="Inactive",0,IF(G12>E12,G12-E12,0)) -> 0 | J12: =IF(L12="Inactive",0,IF(D12>F12,D12-F12,0)) -> 0 | K12: =IF(L12="Inactive",0,IF(E12>G12,E12-G12,0)) -> 0 | L12: Active
A13: NT6 | C13: =IF(B13="","",TEXT(B13,"mmmm")) | E13: =IF(D13="","",D13*$K$4) | G13: =IF(F13="","",F13*$K$4) | H13: =IF(L13="Inactive",0,IF(F13>D13,F13-D13,0)) -> 0 | I13: =IF(L13="Inactive",0,IF(G13>E13,G13-E13,0)) -> 0 | J13: =IF(L13="Inactive",0,IF(D13>F13,D13-F13,0)) -> 0 | K13: =IF(L13="Inactive",0,IF(E13>G13,E13-G13,0)) -> 0 | L13: Active
A14: NT7 | C14: =IF(B14="","",TEXT(B14,"mmmm")) | E14: =IF(D14="","",D14*$K$4) | G14: =IF(F14="","",F14*$K$4) | H14: =IF(L14="Inactive",0,IF(F14>D14,F14-D14,0)) -> 0 | I14: =IF(L14="Inactive",0,IF(G14>E14,G14-E14,0)) -> 0 | J14: =IF(L14="Inactive",0,IF(D14>F14,D14-F14,0)) -> 0 | K14: =IF(L14="Inactive",0,IF(E14>G14,E14-G14,0)) -> 0 | L14: Active
A15: NT8 | C15: =IF(B15="","",TEXT(B15,"mmmm")) | E15: =IF(D15="","",D15*$K$4) | G15: =IF(F15="","",F15*$K$4) | H15: =IF(L15="Inactive",0,IF(F15>D15,F15-D15,0)) -> 0 | I15: =IF(L15="Inactive",0,IF(G15>E15,G15-E15,0)) -> 0 | J15: =IF(L15="Inactive",0,IF(D15>F15,D15-F15,0)) -> 0 | K15: =IF(L15="Inactive",0,IF(E15>G15,E15-G15,0)) -> 0 | L15: Active
A16: NT9 | C16: =IF(B16="","",TEXT(B16,"mmmm")) | E16: =IF(D16="","",D16*$K$4) | G16: =IF(F16="","",F16*$K$4) | H16: =IF(L16="Inactive",0,IF(F16>D16,F16-D16,0)) -> 0 | I16: =IF(L16="Inactive",0,IF(G16>E16,G16-E16,0)) -> 0 | J16: =IF(L16="Inactive",0,IF(D16>F16,D16-F16,0)) -> 0 | K16: =IF(L16="Inactive",0,IF(E16>G16,E16-G16,0)) -> 0 | L16: Active
A17: NT10 | C17: =IF(B17="","",TEXT(B17,"mmmm")) | E17: =IF(D17="","",D17*$K$4) | G17: =IF(F17="","",F17*$K$4) | H17: =IF(L17="Inactive",0,IF(F17>D17,F17-D17,0)) -> 0 | I17: =IF(L17="Inactive",0,IF(G17>E17,G17-E17,0)) -> 0 | J17: =IF(L17="Inactive",0,IF(D17>F17,D17-F17,0)) -> 0 | K17: =IF(L17="Inactive",0,IF(E17>G17,E17-G17,0)) -> 0 | L17: Active
A18: NT11 | C18: =IF(B18="","",TEXT(B18,"mmmm")) | E18: =IF(D18="","",D18*$K$4) | G18: =IF(F18="","",F18*$K$4) | H18: =IF(L18="Inactive",0,IF(F18>D18,F18-D18,0)) -> 0 | I18: =IF(L18="Inactive",0,IF(G18>E18,G18-E18,0)) -> 0 | J18: =IF(L18="Inactive",0,IF(D18>F18,D18-F18,0)) -> 0 | K18: =IF(L18="Inactive",0,IF(E18>G18,E18-G18,0)) -> 0 | L18: Active
A19: NT12 | C19: =IF(B19="","",TEXT(B19,"mmmm")) | E19: =IF(D19="","",D19*$K$4) | G19: =IF(F19="","",F19*$K$4) | H19: =IF(L19="Inactive",0,IF(F19>D19,F19-D19,0)) -> 0 | I19: =IF(L19="Inactive",0,IF(G19>E19,G19-E19,0)) -> 0 | J19: =IF(L19="Inactive",0,IF(D19>F19,D19-F19,0)) -> 0 | K19: =IF(L19="Inactive",0,IF(E19>G19,E19-G19,0)) -> 0 | L19: Active
... A57: NT50 | C57: =IF(B57="","",TEXT(B57,"mmmm")) | E57: =IF(D57="","",D57*$K$4) | G57: =IF(F57="","",F57*$K$4) | H57: =IF(L57="Inactive",0,IF(F57>D57,F57-D57,0)) -> 0 | I57: =IF(L57="Inactive",0,IF(G57>E57,G57-E57,0)) -> 0 | J57: =IF(L57="Inactive",0,IF(D57>F57,D57-F57,0)) -> 0 | K57: =IF(L57="Inactive",0,IF(E57>G57,E57-G57,0)) -> 0 | L57: Active
A58: TOTAL CATEGORY VALUE | D58: =SUM(D8:D57) -> 0 | E58: =SUM(E8:E57) -> 0 | F58: =SUM(F8:F57) -> 0 | G58: =SUM(G8:G57) -> 0 | H58: =SUM(H8:H57) -> 0 | I58: =SUM(I8:I57) -> 0 | J58: =SUM(J8:J57) -> 0 | K58: =SUM(K8:K57) -> 0
A60: 📋 USER GUIDE & OPERATIONAL INSTRUCTIONS
A61: Step 1 — DATA ENTRY
A62: ONLY fill data into columns: 'Product ID' (pre-filled), 'Date of Entry' (Col B), 'Purchase Price JPY' (Col D), and 'Selling Price JPY' (Col F). Do NOT overwrite any other cells — they contain automated formulas!
A63: Step 2 — AUTO DATE TRACKING
A64: The system automatically reads your Date of Entry and extracts the full calendar month name in Column C behind the scenes. No manual entry needed.
A65: Step 3 — AUTO CALCULATIONS
A66: All PHP conversions (Cols E & G), dynamic profit calculations (Cols H & I), and loss flags (Cols J & K) recalculate INSTANTLY whenever you enter or update data.
A67: Step 4 — STOCK STATUS CONTROL
A68: Use the interactive drop-down menu in Column L ('Stock Status') to switch rows between 'Active' and 'Inactive'. Setting a row to 'Inactive' instantly zeroes out its profit and loss contributions from all totals.
A69: Step 5 — QUICK-VIEW LOOKUP
A70: Use the 🔍 dropdown in Cell C5 to instantly surface real-time financial data for any product without scrolling. Results appear in Row 5 immediately.
A71: Step 6 — EXCHANGE RATE
A72: Update Cell K4 with the current JPY/PHP exchange rate. All PHP values across the entire sheet recalculate automatically. Default is 0.37.

Sheet Bleach
A1: KEN JP ANIME FIGURES SHOP
A4: 📦 BLEACH INVENTORY LOG | J4: Live JPY/PHP Rate: | K4: 0.37 | L4: ← Edit here
A5: 🔍 QUICK-VIEW LOOKUP: | C5: ← Select Product ID | E5: =IFERROR(VLOOKUP(C5,A8:L57,4,0),"") | F5: =IFERROR(VLOOKUP(C5,A8:L57,5,0),"") | G5: =IFERROR(VLOOKUP(C5,A8:L57,6,0),"") | H5: =IFERROR(VLOOKUP(C5,A8:L57,7,0),"") | I5: =IFERROR(VLOOKUP(C5,A8:L57,8,0),"") | J5: =IFERROR(VLOOKUP(C5,A8:L57,9,0),"") | K5: =IFERROR(VLOOKUP(C5,A8:L57,10,0),"") | L5: =IFERROR(VLOOKUP(C5,A8:L57,11,0),"")
A7: Product ID | B7: Date of Entry | C7: Transaction Month | D7: Purchase Price (JPY) | E7: Purchase Price (PHP) | F7: Selling Price (JPY) | G7: Selling Price (PHP) | H7: Net Profit (JPY) | I7: Net Profit (PHP) | J7: Net Loss (JPY) | K7: Net Loss (PHP) | L7: Stock Status
A8: BL1 | C8: =IF(B8="","",TEXT(B8,"mmmm")) | E8: =IF(D8="","",D8*$K$4) | G8: =IF(F8="","",F8*$K$4) | H8: =IF(L8="Inactive",0,IF(F8>D8,F8-D8,0)) -> 0 | I8: =IF(L8="Inactive",0,IF(G8>E8,G8-E8,0)) -> 0 | J8: =IF(L8="Inactive",0,IF(D8>F8,D8-F8,0)) -> 0 | K8: =IF(L8="Inactive",0,IF(E8>G8,E8-G8,0)) -> 0 | L8: Active
A9: BL2 | C9: =IF(B9="","",TEXT(B9,"mmmm")) | E9: =IF(D9="","",D9*$K$4) | G9: =IF(F9="","",F9*$K$4) | H9: =IF(L9="Inactive",0,IF(F9>D9,F9-D9,0)) -> 0 | I9: =IF(L9="Inactive",0,IF(G9>E9,G9-E9,0)) -> 0 | J9: =IF(L9="Inactive",0,IF(D9>F9,D9-F9,0)) -> 0 | K9: =IF(L9="Inactive",0,IF(E9>G9,E9-G9,0)) -> 0 | L9: Active
A10: BL3 | C10: =IF(B10="","",TEXT(B10,"mmmm")) | E10: =IF(D10="","",D10*$K$4) | G10: =IF(F10="","",F10*$K$4) | H10: =IF(L10="Inactive",0,IF(F10>D10,F10-D10,0)) -> 0 | I10: =IF(L10="Inactive",0,IF(G10>E10,G10-E10,0)) -> 0 | J10: =IF(L10="Inactive",0,IF(D10>F10,D10-F10,0)) -> 0 | K10: =IF(L10="Inactive",0,IF(E10>G10,E10-G10,0)) -> 0 | L10: Active
A11: BL4 | C11: =IF(B11="","",TEXT(B11,"mmmm")) | E11: =IF(D11="","",D11*$K$4) | G11: =IF(F11="","",F11*$K$4) | H11: =IF(L11="Inactive",0,IF(F11>D11,F11-D11,0)) -> 0 | I11: =IF(L11="Inactive",0,IF(G11>E11,G11-E11,0)) -> 0 | J11: =IF(L11="Inactive",0,IF(D11>F11,D11-F11,0)) -> 0 | K11: =IF(L11="Inactive",0,IF(E11>G11,E11-G11,0)) -> 0 | L11: Active
A12: BL5 | C12: =IF(B12="","",TEXT(B12,"mmmm")) | E12: =IF(D12="","",D12*$K$4) | G12: =IF(F12="","",F12*$K$4) | H12: =IF(L12="Inactive",0,IF(F12>D12,F12-D12,0)) -> 0 | I12: =IF(L12="Inactive",0,IF(G12>E12,G12-E12,0)) -> 0 | J12: =IF(L12="Inactive",0,IF(D12>F12,D12-F12,0)) -> 0 | K12: =IF(L12="Inactive",0,IF(E12>G12,E12-G12,0)) -> 0 | L12: Active
A13: BL6 | C13: =IF(B13="","",TEXT(B13,"mmmm")) | E13: =IF(D13="","",D13*$K$4) | G13: =IF(F13="","",F13*$K$4) | H13: =IF(L13="Inactive",0,IF(F13>D13,F13-D13,0)) -> 0 | I13: =IF(L13="Inactive",0,IF(G13>E13,G13-E13,0)) -> 0 | J13: =IF(L13="Inactive",0,IF(D13>F13,D13-F13,0)) -> 0 | K13: =IF(L13="Inactive",0,IF(E13>G13,E13-G13,0)) -> 0 | L13: Active
A14: BL7 | C14: =IF(B14="","",TEXT(B14,"mmmm")) | E14: =IF(D14="","",D14*$K$4) | G14: =IF(F14="","",F14*$K$4) | H14: =IF(L14="Inactive",0,IF(F14>D14,F14-D14,0)) -> 0 | I14: =IF(L14="Inactive",0,IF(G14>E14,G14-E14,0)) -> 0 | J14: =IF(L14="Inactive",0,IF(D14>F14,D14-F14,0)) -> 0 | K14: =IF(L14="Inactive",0,IF(E14>G14,E14-G14,0)) -> 0 | L14: Active
A15: BL8 | C15: =IF(B15="","",TEXT(B15,"mmmm")) | E15: =IF(D15="","",D15*$K$4) | G15: =IF(F15="","",F15*$K$4) | H15: =IF(L15="Inactive",0,IF(F15>D15,F15-D15,0)) -> 0 | I15: =IF(L15="Inactive",0,IF(G15>E15,G15-E15,0)) -> 0 | J15: =IF(L15="Inactive",0,IF(D15>F15,D15-F15,0)) -> 0 | K15: =IF(L15="Inactive",0,IF(E15>G15,E15-G15,0)) -> 0 | L15: Active
A16: BL9 | C16: =IF(B16="","",TEXT(B16,"mmmm")) | E16: =IF(D16="","",D16*$K$4) | G16: =IF(F16="","",F16*$K$4) | H16: =IF(L16="Inactive",0,IF(F16>D16,F16-D16,0)) -> 0 | I16: =IF(L16="Inactive",0,IF(G16>E16,G16-E16,0)) -> 0 | J16: =IF(L16="Inactive",0,IF(D16>F16,D16-F16,0)) -> 0 | K16: =IF(L16="Inactive",0,IF(E16>G16,E16-G16,0)) -> 0 | L16: Active
A17: BL10 | C17: =IF(B17="","",TEXT(B17,"mmmm")) | E17: =IF(D17="","",D17*$K$4) | G17: =IF(F17="","",F17*$K$4) | H17: =IF(L17="Inactive",0,IF(F17>D17,F17-D17,0)) -> 0 | I17: =IF(L17="Inactive",0,IF(G17>E17,G17-E17,0)) -> 0 | J17: =IF(L17="Inactive",0,IF(D17>F17,D17-F17,0)) -> 0 | K17: =IF(L17="Inactive",0,IF(E17>G17,E17-G17,0)) -> 0 | L17: Active
A18: BL11 | C18: =IF(B18="","",TEXT(B18,"mmmm")) | E18: =IF(D18="","",D18*$K$4) | G18: =IF(F18="","",F18*$K$4) | H18: =IF(L18="Inactive",0,IF(F18>D18,F18-D18,0)) -> 0 | I18: =IF(L18="Inactive",0,IF(G18>E18,G18-E18,0)) -> 0 | J18: =IF(L18="Inactive",0,IF(D18>F18,D18-F18,0)) -> 0 | K18: =IF(L18="Inactive",0,IF(E18>G18,E18-G18,0)) -> 0 | L18: Active
A19: BL12 | C19: =IF(B19="","",TEXT(B19,"mmmm")) | E19: =IF(D19="","",D19*$K$4) | G19: =IF(F19="","",F19*$K$4) | H19: =IF(L19="Inactive",0,IF(F19>D19,F19-D19,0)) -> 0 | I19: =IF(L19="Inactive",0,IF(G19>E19,G19-E19,0)) -> 0 | J19: =IF(L19="Inactive",0,IF(D19>F19,D19-F19,0)) -> 0 | K19: =IF(L19="Inactive",0,IF(E19>G19,E19-G19,0)) -> 0 | L19: Active
... A57: BL50 | C57: =IF(B57="","",TEXT(B57,"mmmm")) | E57: =IF(D57="","",D57*$K$4) | G57: =IF(F57="","",F57*$K$4) | H57: =IF(L57="Inactive",0,IF(F57>D57,F57-D57,0)) -> 0 | I57: =IF(L57="Inactive",0,IF(G57>E57,G57-E57,0)) -> 0 | J57: =IF(L57="Inactive",0,IF(D57>F57,D57-F57,0)) -> 0 | K57: =IF(L57="Inactive",0,IF(E57>G57,E57-G57,0)) -> 0 | L57: Active
A58: TOTAL CATEGORY VALUE | D58: =SUM(D8:D57) -> 0 | E58: =SUM(E8:E57) -> 0 | F58: =SUM(F8:F57) -> 0 | G58: =SUM(G8:G57) -> 0 | H58: =SUM(H8:H57) -> 0 | I58: =SUM(I8:I57) -> 0 | J58: =SUM(J8:J57) -> 0 | K58: =SUM(K8:K57) -> 0
A60: 📋 USER GUIDE & OPERATIONAL INSTRUCTIONS
A61: Step 1 — DATA ENTRY
A62: ONLY fill data into columns: 'Product ID' (pre-filled), 'Date of Entry' (Col B), 'Purchase Price JPY' (Col D), and 'Selling Price JPY' (Col F). Do NOT overwrite any other cells — they contain automated formulas!
A63: Step 2 — AUTO DATE TRACKING
A64: The system automatically reads your Date of Entry and extracts the full calendar month name in Column C behind the scenes. No manual entry needed.
A65: Step 3 — AUTO CALCULATIONS
A66: All PHP conversions (Cols E & G), dynamic profit calculations (Cols H & I), and loss flags (Cols J & K) recalculate INSTANTLY whenever you enter or update data.
A67: Step 4 — STOCK STATUS CONTROL
A68: Use the interactive drop-down menu in Column L ('Stock Status') to switch rows between 'Active' and 'Inactive'. Setting a row to 'Inactive' instantly zeroes out its profit and loss contributions from all totals.
A69: Step 5 — QUICK-VIEW LOOKUP
A70: Use the 🔍 dropdown in Cell C5 to instantly surface real-time financial data for any product without scrolling. Results appear in Row 5 immediately.
A71: Step 6 — EXCHANGE RATE
A72: Update Cell K4 with the current JPY/PHP exchange rate. All PHP values across the entire sheet recalculate automatically. Default is 0.37.

Sheet My Hero Academia
A1: KEN JP ANIME FIGURES SHOP
A4: 📦 MY HERO ACADEMIA INVENTORY LOG | J4: Live JPY/PHP Rate: | K4: 0.37 | L4: ← Edit here
A5: 🔍 QUICK-VIEW LOOKUP: | C5: ← Select Product ID | E5: =IFERROR(VLOOKUP(C5,A8:L57,4,0),"") | F5: =IFERROR(VLOOKUP(C5,A8:L57,5,0),"") | G5: =IFERROR(VLOOKUP(C5,A8:L57,6,0),"") | H5: =IFERROR(VLOOKUP(C5,A8:L57,7,0),"") | I5: =IFERROR(VLOOKUP(C5,A8:L57,8,0),"") | J5: =IFERROR(VLOOKUP(C5,A8:L57,9,0),"") | K5: =IFERROR(VLOOKUP(C5,A8:L57,10,0),"") | L5: =IFERROR(VLOOKUP(C5,A8:L57,11,0),"")
A7: Product ID | B7: Date of Entry | C7: Transaction Month | D7: Purchase Price (JPY) | E7: Purchase Price (PHP) | F7: Selling Price (JPY) | G7: Selling Price (PHP) | H7: Net Profit (JPY) | I7: Net Profit (PHP) | J7: Net Loss (JPY) | K7: Net Loss (PHP) | L7: Stock Status
A8: MHA1 | C8: =IF(B8="","",TEXT(B8,"mmmm")) | E8: =IF(D8="","",D8*$K$4) | G8: =IF(F8="","",F8*$K$4) | H8: =IF(L8="Inactive",0,IF(F8>D8,F8-D8,0)) -> 0 | I8: =IF(L8="Inactive",0,IF(G8>E8,G8-E8,0)) -> 0 | J8: =IF(L8="Inactive",0,IF(D8>F8,D8-F8,0)) -> 0 | K8: =IF(L8="Inactive",0,IF(E8>G8,E8-G8,0)) -> 0 | L8: Active
A9: MHA2 | C9: =IF(B9="","",TEXT(B9,"mmmm")) | E9: =IF(D9="","",D9*$K$4) | G9: =IF(F9="","",F9*$K$4) | H9: =IF(L9="Inactive",0,IF(F9>D9,F9-D9,0)) -> 0 | I9: =IF(L9="Inactive",0,IF(G9>E9,G9-E9,0)) -> 0 | J9: =IF(L9="Inactive",0,IF(D9>F9,D9-F9,0)) -> 0 | K9: =IF(L9="Inactive",0,IF(E9>G9,E9-G9,0)) -> 0 | L9: Active
A10: MHA3 | C10: =IF(B10="","",TEXT(B10,"mmmm")) | E10: =IF(D10="","",D10*$K$4) | G10: =IF(F10="","",F10*$K$4) | H10: =IF(L10="Inactive",0,IF(F10>D10,F10-D10,0)) -> 0 | I10: =IF(L10="Inactive",0,IF(G10>E10,G10-E10,0)) -> 0 | J10: =IF(L10="Inactive",0,IF(D10>F10,D10-F10,0)) -> 0 | K10: =IF(L10="Inactive",0,IF(E10>G10,E10-G10,0)) -> 0 | L10: Active
A11: MHA4 | C11: =IF(B11="","",TEXT(B11,"mmmm")) | E11: =IF(D11="","",D11*$K$4) | G11: =IF(F11="","",F11*$K$4) | H11: =IF(L11="Inactive",0,IF(F11>D11,F11-D11,0)) -> 0 | I11: =IF(L11="Inactive",0,IF(G11>E11,G11-E11,0)) -> 0 | J11: =IF(L11="Inactive",0,IF(D11>F11,D11-F11,0)) -> 0 | K11: =IF(L11="Inactive",0,IF(E11>G11,E11-G11,0)) -> 0 | L11: Active
A12: MHA5 | C12: =IF(B12="","",TEXT(B12,"mmmm")) | E12: =IF(D12="","",D12*$K$4) | G12: =IF(F12="","",F12*$K$4) | H12: =IF(L12="Inactive",0,IF(F12>D12,F12-D12,0)) -> 0 | I12: =IF(L12="Inactive",0,IF(G12>E12,G12-E12,0)) -> 0 | J12: =IF(L12="Inactive",0,IF(D12>F12,D12-F12,0)) -> 0 | K12: =IF(L12="Inactive",0,IF(E12>G12,E12-G12,0)) -> 0 | L12: Active
A13: MHA6 | C13: =IF(B13="","",TEXT(B13,"mmmm")) | E13: =IF(D13="","",D13*$K$4) | G13: =IF(F13="","",F13*$K$4) | H13: =IF(L13="Inactive",0,IF(F13>D13,F13-D13,0)) -> 0 | I13: =IF(L13="Inactive",0,IF(G13>E13,G13-E13,0)) -> 0 | J13: =IF(L13="Inactive",0,IF(D13>F13,D13-F13,0)) -> 0 | K13: =IF(L13="Inactive",0,IF(E13>G13,E13-G13,0)) -> 0 | L13: Active
A14: MHA7 | C14: =IF(B14="","",TEXT(B14,"mmmm")) | E14: =IF(D14="","",D14*$K$4) | G14: =IF(F14="","",F14*$K$4) | H14: =IF(L14="Inactive",0,IF(F14>D14,F14-D14,0)) -> 0 | I14: =IF(L14="Inactive",0,IF(G14>E14,G14-E14,0)) -> 0 | J14: =IF(L14="Inactive",0,IF(D14>F14,D14-F14,0)) -> 0 | K14: =IF(L14="Inactive",0,IF(E14>G14,E14-G14,0)) -> 0 | L14: Active
A15: MHA8 | C15: =IF(B15="","",TEXT(B15,"mmmm")) | E15: =IF(D15="","",D15*$K$4) | G15: =IF(F15="","",F15*$K$4) | H15: =IF(L15="Inactive",0,IF(F15>D15,F15-D15,0)) -> 0 | I15: =IF(L15="Inactive",0,IF(G15>E15,G15-E15,0)) -> 0 | J15: =IF(L15="Inactive",0,IF(D15>F15,D15-F15,0)) -> 0 | K15: =IF(L15="Inactive",0,IF(E15>G15,E15-G15,0)) -> 0 | L15: Active
A16: MHA9 | C16: =IF(B16="","",TEXT(B16,"mmmm")) | E16: =IF(D16="","",D16*$K$4) | G16: =IF(F16="","",F16*$K$4) | H16: =IF(L16="Inactive",0,IF(F16>D16,F16-D16,0)) -> 0 | I16: =IF(L16="Inactive",0,IF(G16>E16,G16-E16,0)) -> 0 | J16: =IF(L16="Inactive",0,IF(D16>F16,D16-F16,0)) -> 0 | K16: =IF(L16="Inactive",0,IF(E16>G16,E16-G16,0)) -> 0 | L16: Active
A17: MHA10 | C17: =IF(B17="","",TEXT(B17,"mmmm")) | E17: =IF(D17="","",D17*$K$4) | G17: =IF(F17="","",F17*$K$4) | H17: =IF(L17="Inactive",0,IF(F17>D17,F17-D17,0)) -> 0 | I17: =IF(L17="Inactive",0,IF(G17>E17,G17-E17,0)) -> 0 | J17: =IF(L17="Inactive",0,IF(D17>F17,D17-F17,0)) -> 0 | K17: =IF(L17="Inactive",0,IF(E17>G17,E17-G17,0)) -> 0 | L17: Active
A18: MHA11 | C18: =IF(B18="","",TEXT(B18,"mmmm")) | E18: =IF(D18="","",D18*$K$4) | G18: =IF(F18="","",F18*$K$4) | H18: =IF(L18="Inactive",0,IF(F18>D18,F18-D18,0)) -> 0 | I18: =IF(L18="Inactive",0,IF(G18>E18,G18-E18,0)) -> 0 | J18: =IF(L18="Inactive",0,IF(D18>F18,D18-F18,0)) -> 0 | K18: =IF(L18="Inactive",0,IF(E18>G18,E18-G18,0)) -> 0 | L18: Active
A19: MHA12 | C19: =IF(B19="","",TEXT(B19,"mmmm")) | E19: =IF(D19="","",D19*$K$4) | G19: =IF(F19="","",F19*$K$4) | H19: =IF(L19="Inactive",0,IF(F19>D19,F19-D19,0)) -> 0 | I19: =IF(L19="Inactive",0,IF(G19>E19,G19-E19,0)) -> 0 | J19: =IF(L19="Inactive",0,IF(D19>F19,D19-F19,0)) -> 0 | K19: =IF(L19="Inactive",0,IF(E19>G19,E19-G19,0)) -> 0 | L19: Active
... A57: MHA50 | C57: =IF(B57="","",TEXT(B57,"mmmm")) | E57: =IF(D57="","",D57*$K$4) | G57: =IF(F57="","",F57*$K$4) | H57: =IF(L57="Inactive",0,IF(F57>D57,F57-D57,0)) -> 0 | I57: =IF(L57="Inactive",0,IF(G57>E57,G57-E57,0)) -> 0 | J57: =IF(L57="Inactive",0,IF(D57>F57,D57-F57,0)) -> 0 | K57: =IF(L57="Inactive",0,IF(E57>G57,E57-G57,0)) -> 0 | L57: Active
A58: TOTAL CATEGORY VALUE | D58: =SUM(D8:D57) -> 0 | E58: =SUM(E8:E57) -> 0 | F58: =SUM(F8:F57) -> 0 | G58: =SUM(G8:G57) -> 0 | H58: =SUM(H8:H57) -> 0 | I58: =SUM(I8:I57) -> 0 | J58: =SUM(J8:J57) -> 0 | K58: =SUM(K8:K57) -> 0
A60: 📋 USER GUIDE & OPERATIONAL INSTRUCTIONS
A61: Step 1 — DATA ENTRY
A62: ONLY fill data into columns: 'Product ID' (pre-filled), 'Date of Entry' (Col B), 'Purchase Price JPY' (Col D), and 'Selling Price JPY' (Col F). Do NOT overwrite any other cells — they contain automated formulas!
A63: Step 2 — AUTO DATE TRACKING
A64: The system automatically reads your Date of Entry and extracts the full calendar month name in Column C behind the scenes. No manual entry needed.
A65: Step 3 — AUTO CALCULATIONS
A66: All PHP conversions (Cols E & G), dynamic profit calculations (Cols H & I), and loss flags (Cols J & K) recalculate INSTANTLY whenever you enter or update data.
A67: Step 4 — STOCK STATUS CONTROL
A68: Use the interactive drop-down menu in Column L ('Stock Status') to switch rows between 'Active' and 'Inactive'. Setting a row to 'Inactive' instantly zeroes out its profit and loss contributions from all totals.
A69: Step 5 — QUICK-VIEW LOOKUP
A70: Use the 🔍 dropdown in Cell C5 to instantly surface real-time financial data for any product without scrolling. Results appear in Row 5 immediately.
A71: Step 6 — EXCHANGE RATE
A72: Update Cell K4 with the current JPY/PHP exchange rate. All PHP values across the entire sheet recalculate automatically. Default is 0.37.

Sheet Overall Analytics
A1: KEN JP ANIME FIGURES SHOP — EXECUTIVE ANALYTICS DASHBOARD
A4: 📊 CONSOLIDATED KPI MATRIX — LIVE CATEGORY PERFORMANCE | F4: 🎯 REAL-TIME BUSINESS INTELLIGENCE METRICS
A5: Anime Category | B5: Monthly Purchase Vol (JPY) | C5: Monthly Profit (JPY) | D5: Monthly Losses (JPY) | F5: CARD A — Overall Business Profit Margin (%)
A6: One Piece | B6: ='One Piece'!D58 -> 0 | C6: ='One Piece'!H58 -> 0 | D6: ='One Piece'!J58 -> 0 | F6: =IFERROR(C11/(B11+C11),"No Data") -> No Data
A7: Dragon Ball Z | B7: ='Dragon Ball Z'!D58 -> 0 | C7: ='Dragon Ball Z'!H58 -> 0 | D7: ='Dragon Ball Z'!J58 -> 0
A8: Naruto | B8: =Naruto!D58 -> 0 | C8: =Naruto!H58 -> 0 | D8: =Naruto!J58 -> 0
A9: Bleach | B9: =Bleach!D58 -> 0 | C9: =Bleach!H58 -> 0 | D9: =Bleach!J58 -> 0 | F9: Formula: Total Profit ÷ (Total Purchase + Total Profit)
A10: My Hero Academia | B10: ='My Hero Academia'!D58 -> 0 | C10: ='My Hero Academia'!H58 -> 0 | D10: ='My Hero Academia'!J58 -> 0 | F10: CARD B — Top Revenue-Generating Anime Category
A11: OVERALL TOTALS | B11: =SUM(B6:B10) -> 0 | C11: =SUM(C6:C10) -> 0 | D11: =SUM(D6:D10) -> 0 | F11: =IFERROR(INDEX(A6:A10,MATCH(MAX(C6:C10),C6:C10,0)),"No Data") -> One Piece
A13: 📈 ADDITIONAL KPI SUMMARY
A14: Total Capital Deployed (JPY) | B14: =B11 -> 0 | F14: Formula: INDEX/MATCH on MAX Monthly Profit across all categories
A15: Total Net Profit (JPY) | B15: =C11 -> 0
A16: Total Net Loss (JPY) | B16: =D11 -> 0
A17: Net P&L (JPY) | B17: =C11-D11 -> 0
A20: 📊 HOW TO INSERT THE PERFORMANCE CHART — READ BEFORE BUILDING
A21: 1. Select cells A5:D10 (the KPI Matrix including headers and 5 category rows — do NOT include the Totals row).
A22: 2. Go to the 'Insert' tab → click 'Insert Column or Bar Chart' → choose 'Clustered Column'.
A23: 3. Right-click the chart → 'Select Data' → confirm Series are: Purchase Vol (JPY), Monthly Profit (JPY), Monthly Losses (JPY).
A24: 4. Click the 'Purchase Volume' bar series → Format → Fill → Solid Fill → Color: #6C757D (Cool Gray).
A25: 5. Click the 'Monthly Profit' bar series → Format → Fill → Solid Fill → Color: #28A745 (Emerald Green).
A26: 6. Click the 'Monthly Losses' bar series → Format → Fill → Solid Fill → Color: #DC3545 (Crimson Red).
A27: 7. Click on Gridlines → press DELETE to remove all horizontal gridline clutter for a clean flat look.
A28: 8. Click the Chart Border → Format → No Line. Remove the default chart box border.
A29: 9. Double-click the Chart Title and type: 'Financial Performance & Capital Allocation Analytics'.
A30: 10. Drag and resize the chart to fit approximately cells A20:J40 on this dashboard sheet.

Sheet VBA & Setup Guide
A1: VBA MACRO CODE & SETUP INSTRUCTIONS — KEN JP ANIME FIGURES SHOP
A4: SECTION 1: VBA SEARCH MACRO CODE
A5: Copy the code below into the VBA Editor (Alt+F11 → Insert → Module):
A7: Sub SearchByProductName()
A8: ' ─────────────────────────────────────────────────────────────────
A9: ' KEN JP ANIME FIGURES SHOP — Product Search Macro v1.0
A10: ' Searches Column A of the active sheet for a Product ID match
A11: ' ─────────────────────────────────────────────────────────────────
A12: Dim searchID As String
A13: Dim foundCell As Range
A14: Dim lastRow As Long
A15: Dim ws As Worksheet
... A85: Conditional formatting automatically applies green for Active, red for Inactive.
